acnestis/__init__.py
acnestis/command.py
acnestis/processing.py
acnestis/steps.py
acnestis/yaml.py
acnestis-0.1.1.dist-info/METADATA
acnestis-0.1.1.dist-info/WHEEL
acnestis-0.1.1.dist-info/entry_points.txt
acnestis-0.1.1.dist-info/RECORD
