Metadata-Version: 2.1
Name: acnestis
Version: 0.1.1
Summary: data collection, aggregation and convertion tool
Home-page: https://github.com/oduvan/acnestis
License: MIT
Author: oduvan
Author-email: a.lyabah@checkio.org
Requires-Python: >3.8
Classifier: License :: OSI Approved :: MIT License
Classifier: Programming Language :: Python :: 3
Classifier: Programming Language :: Python :: 3.9
Classifier: Programming Language :: Python :: 3.10
Classifier: Programming Language :: Python :: 3.11
Requires-Dist: docker (>=6.1.3,<7.0.0)
Requires-Dist: gitpython (>=3.1.31,<4.0.0)
Requires-Dist: pyyaml (>=6.0,<7.0)
Project-URL: Repository, https://github.com/oduvan/acnestis
